sentry_streams-0.0.34.dist-info/METADATA
sentry_streams-0.0.34.dist-info/WHEEL
sentry_streams/__init__.py
sentry_streams/adapters/__init__.py
sentry_streams/adapters/arroyo/__init__.py
sentry_streams/adapters/arroyo/adapter.py
sentry_streams/adapters/arroyo/broadcaster.py
sentry_streams/adapters/arroyo/consumer.py
sentry_streams/adapters/arroyo/forwarder.py
sentry_streams/adapters/arroyo/msg_wrapper.py
sentry_streams/adapters/arroyo/multi_process_delegate.py
sentry_streams/adapters/arroyo/reduce.py
sentry_streams/adapters/arroyo/reduce_delegate.py
sentry_streams/adapters/arroyo/routers.py
sentry_streams/adapters/arroyo/routes.py
sentry_streams/adapters/arroyo/rust_arroyo.py
sentry_streams/adapters/arroyo/rust_step.py
sentry_streams/adapters/arroyo/steps.py
sentry_streams/adapters/arroyo/steps_chain.py
sentry_streams/adapters/loader.py
sentry_streams/adapters/stream_adapter.py
sentry_streams/config.json
sentry_streams/config_types.py
sentry_streams/deployment_config/README.md
sentry_streams/deployment_config/blq.yaml
sentry_streams/deployment_config/flink_blq.yaml
sentry_streams/deployment_config/flink_transformer.yaml
sentry_streams/deployment_config/gcs_sink.yaml
sentry_streams/deployment_config/parallel_processing.yaml
sentry_streams/deployment_config/simple_batching.yaml
sentry_streams/deployment_config/simple_map_filter.yaml
sentry_streams/deployment_config/test_flink.yaml
sentry_streams/deployment_config/transformer.yaml
sentry_streams/dummy/__init__.py
sentry_streams/dummy/dummy_adapter.py
sentry_streams/examples/__init__.py
sentry_streams/examples/alerts.py
sentry_streams/examples/batching.py
sentry_streams/examples/billing.py
sentry_streams/examples/blq.py
sentry_streams/examples/blq_fn.py
sentry_streams/examples/broadcast.py
sentry_streams/examples/broadcast_fn.py
sentry_streams/examples/events.py
sentry_streams/examples/gcs_sink.py
sentry_streams/examples/parallel_processing.py
sentry_streams/examples/parquet_serializer.py
sentry_streams/examples/rust_simple_map_filter/pipeline.py
sentry_streams-0.0.34.dist-info/RECORD
