Metadata-Version: 2.4
Name: sentry-streams
Version: 0.0.34
Requires-Dist: requests>=2.32.3
Requires-Dist: sentry-arroyo>=2.35.0
Requires-Dist: pyyaml>=6.0.2
Requires-Dist: jsonschema>=4.23.0
Requires-Dist: sentry-kafka-schemas>=1.2.0
Requires-Dist: polars
Requires-Dist: click>=8.1.7
Requires-Dist: datadog>=0.49.1
Summary: The python Sentry Streaming API
Requires-Python: >=3.11
